{
  "hot": {
    "note": "统计3日内新投稿的数据综合得分，每十分钟更新一次。",
    "code": 0,
    "pages": 1,
    "num": 10,
    "list": [
      {
        "aid": "6854614",
        "typename": "广告",
        "title": "绅士必撸的日本美女广告合集（加强版）",
        "subtitle": "",
        "play": 46135,
        "review": 0,
        "video_review": 700,
        "favorites": 1307,
        "mid": 36296254,
        "author": "辣麽鸡炖",
        "description": "YouTube https://www.youtube.com/channel/UCuTNcnGVHRlEJ7uq-X8mfTQ \n更多有趣儿的视频请订阅:「辣麽鸡炖」新浪微博：「辣么鸡炖」今日头条 「辣么鸡炖」 我的淘宝：「http://pkonline.taobao.com」",
        "create": "2016-10-28 12:53",
        "pic": "http://i0.hdslb.com/bfs/archive/919fbd2d70c2ecccade71a7d13c1f9addb2e337c.jpg_320x200.jpg",
        "coins": 88,
        "duration": "13:50",
        "badgepay": false,
        "pts": 54916
      },
      {
        "aid": "6858481",
        "typename": "广告",
        "title": "【迷之广告】你能猜出这是什么广告吗？第四弹",
        "subtitle": "",
        "play": 33507,
        "review": 1,
        "video_review": 821,
        "favorites": 632,
        "mid": 7760828,
        "author": "喜仔的世界",
        "description": "youtube.com/watch?v=jdiinDZF8bI&amp;amp;feature=youtu.be 欢迎加入喜仔QQ轰趴群：531829163 微博@喜仔的世界",
        "create": "2016-10-28 18:10",
        "pic": "http://i0.hdslb.com/bfs/archive/966a97dabf2522fc8b4ae5c84039946ae1f5ee8a.jpg_320x200.jpg",
        "coins": 332,
        "duration": "8:26",
        "badgepay": false,
        "pts": 37078
      },
      {
        "aid": "6847151",
        "typename": "广告",
        "title": "【妈的智障】你可曾见过如此形象的纸巾广告",
        "subtitle": "",
        "play": 20500,
        "review": 0,
        "video_review": 66,
        "favorites": 179,
        "mid": 31152796,
        "author": "墨小伟MMO",
        "description": "http://7rflo2.com2.z0.glb.qiniucdn.com/578c9e4592664_lower.mp4 擦屁股内快=-=",
        "create": "2016-10-27 19:34",
        "pic": "http://i1.hdslb.com/bfs/archive/92823d5be3670be97def7cae9d63a812d33bc52c.jpg_320x200.jpg",
        "coins": 42,
        "duration": "1:05",
        "badgepay": false,
        "pts": 20171
      },
      {
        "aid": "6847918",
        "typename": "广告",
        "title": "史上最励志的广告",
        "subtitle": "",
        "play": 12392,
        "review": 0,
        "video_review": 54,
        "favorites": 417,
        "mid": 1327168,
        "author": "斯旺西之虎Jaegerbomb",
        "description": "https://www.youtube.com/watch?v=pWP2HEfZ0gI A man is not a man when he fucks, nor when he makes millions of pounds. A man becomes a man when he fights and I don't give a fuck you are homeless, or whitecollar, or rich or a student. You can box if you ",
        "create": "2016-10-27 20:43",
        "pic": "http://i0.hdslb.com/bfs/archive/47db6f5fac80b5b76b7f53b23011b90b34d5d1f8.jpg_320x200.jpg",
        "coins": 56,
        "duration": "144",
        "badgepay": false,
        "pts": 15220
      },
      {
        "aid": "6858601",
        "typename": "广告",
        "title": "在我们手中的，不只是一块屏幕，而是通往未来世界的门",
        "subtitle": "",
        "play": 14338,
        "review": 0,
        "video_review": 200,
        "favorites": 145,
        "mid": 23920239,
        "author": "小米公司",
        "description": "越看不见的，越想去看；越不知道的，越想要答案，这就是带领我们不断打开未知的好奇心。在我们手中的，不只是一块屏幕，而是通往未来世界的门。",
        "create": "2016-10-28 18:19",
        "pic": "http://i1.hdslb.com/bfs/archive/b5e6919b770e47cce3c9bdd2c28451742e4b5cd1.jpg_320x200.jpg",
        "coins": 272,
        "duration": "1:03",
        "badgepay": false,
        "pts": 14499
      },
      {
        "aid": "6846109",
        "typename": "广告",
        "title": "日产NISSAN 关爱喵星人公益广告（中文字幕）",
        "subtitle": "",
        "play": 10968,
        "review": 0,
        "video_review": 22,
        "favorites": 335,
        "mid": 26262275,
        "author": "草莓坏坏",
        "description": "YouTube搬运作品，原地址：https://www.youtube.com/watch?v=XXXMpCwujF0 原作者：廣告裁判 ",
        "create": "2016-10-27 17:56",
        "pic": "http://i2.hdslb.com/bfs/archive/afa808afe04a2ccdcba2765adf7b8c14c182b150.jpg_320x200.jpg",
        "coins": 94,
        "duration": "0:51",
        "badgepay": false,
        "pts": 13028
      },
      {
        "aid": "6868409",
        "typename": "广告",
        "title": "1985年的日本电视广告就已经不堪入目了",
        "subtitle": "",
        "play": 11842,
        "review": 0,
        "video_review": 154,
        "favorites": 75,
        "mid": 36296254,
        "author": "辣麽鸡炖",
        "description": "YouTube https://www.youtube.com/watch?v=y7HJ7zBHLyA \n\n更多有趣儿的视频请订阅:「辣麽鸡炖」新浪微博：「辣么鸡炖」今日头条 「辣么鸡炖」 我的淘宝：「http://pkonline.taobao.com」",
        "create": "2016-10-29 12:08",
        "pic": "http://i2.hdslb.com/bfs/archive/363abfa9b7a130a6c4a6b15a1a316cc9efa603b4.jpg_320x200.jpg",
        "coins": 6,
        "duration": "12:21",
        "badgepay": false,
        "pts": 11488
      },
      {
        "aid": "6845615",
        "typename": "广告",
        "title": "【创意广告】泰国搞笑巧克力威化饼广告《没有人可以抢走我的巧克力饼干》（中文字幕）",
        "subtitle": "",
        "play": 10361,
        "review": 0,
        "video_review": 52,
        "favorites": 121,
        "mid": 26262275,
        "author": "草莓坏坏",
        "description": "YouTube搬运作品，原地址：https://www.youtube.com/watch?v=g8VtCo0yRoM 原作者：廣告裁判 ",
        "create": "2016-10-27 17:13",
        "pic": "http://i2.hdslb.com/bfs/archive/71df8c16c977fd77904c20948d933c3ee25c5da8.jpg_320x200.jpg",
        "coins": 26,
        "duration": "0:57",
        "badgepay": false,
        "pts": 10479
      },
      {
        "aid": "6847045",
        "typename": "广告",
        "title": "【妈的智障】捷豹公司挤兑奔驰公司的鸡头广告",
        "subtitle": "",
        "play": 7997,
        "review": 0,
        "video_review": 38,
        "favorites": 119,
        "mid": 31152796,
        "author": "墨小伟MMO",
        "description": "http://7ryl2t.com1.z0.glb.clouddn.com/57a04f06a5177.mp4 不到为啥 只是想笑",
        "create": "2016-10-27 19:24",
        "pic": "http://i1.hdslb.com/bfs/archive/6cd9595fbf3944e2ae8bd32ebaf1131dc540d8ca.jpg_320x200.jpg",
        "coins": 19,
        "duration": "1:30",
        "badgepay": false,
        "pts": 8328
      },
      {
        "aid": "6851973",
        "typename": "广告",
        "title": "老外的泡面广告是这样的【这脑洞我服】",
        "subtitle": "",
        "play": 8571,
        "review": 0,
        "video_review": 11,
        "favorites": 29,
        "mid": 28104030,
        "author": "鲶鱼酱家的小白熊",
        "description": "https://youtu.be/SZWyKvpkTRk 【原标题】Yatekomo Los Originales con Jorge Cremades &amp;amp; Dani Rovira\n来自up的小科普：此为一家名为【gallina blanca】的鸡精 生产公司 旗下的速食品牌系列的一款方便面。。。比康师傅贵了一倍，up实际测试完全吃不饱",
        "create": "2016-10-28 05:54",
        "pic": "http://i1.hdslb.com/bfs/archive/0a2d396dc51f9af8ef8ad64214f527d6091dd7d8.jpg_320x200.jpg",
        "coins": 3,
        "duration": "0:44",
        "badgepay": false,
        "pts": 7981
      }
    ]
  },
  "hot_original": {
    "note": "统计3日内新投稿的数据综合得分，每十分钟更新一次。",
    "code": 0,
    "pages": 1,
    "num": 7,
    "list": [
      {
        "aid": "6858601",
        "typename": "广告",
        "title": "在我们手中的，不只是一块屏幕，而是通往未来世界的门",
        "subtitle": "",
        "play": 14338,
        "review": 0,
        "video_review": 200,
        "favorites": 145,
        "mid": 23920239,
        "author": "小米公司",
        "description": "越看不见的，越想去看；越不知道的，越想要答案，这就是带领我们不断打开未知的好奇心。在我们手中的，不只是一块屏幕，而是通往未来世界的门。",
        "create": "2016-10-28 18:19",
        "pic": "http://i1.hdslb.com/bfs/archive/b5e6919b770e47cce3c9bdd2c28451742e4b5cd1.jpg_320x200.jpg",
        "coins": 272,
        "duration": "1:03",
        "badgepay": false,
        "pts": 14499
      },
      {
        "aid": "6847439",
        "typename": "广告",
        "title": "途虎独家！最新美少女天团SNH48大片拍摄花絮",
        "subtitle": "",
        "play": 597,
        "review": 0,
        "video_review": 4,
        "favorites": 6,
        "mid": 52229078,
        "author": "月月爱车",
        "description": "途虎独家！最新美少女天团SNH48大片拍摄花絮",
        "create": "2016-10-27 20:00",
        "pic": "http://i0.hdslb.com/bfs/archive/2c017cc66eda565192f87966673ca50919931127.png_320x200.png",
        "coins": 33,
        "duration": "1:40",
        "badgepay": false,
        "pts": 270
      },
      {
        "aid": "6885482",
        "typename": "广告",
        "title": "红色预警！从釜山开往重庆的列车圣诞抵达，你敢去接吗？",
        "subtitle": "",
        "play": 216,
        "review": 0,
        "video_review": 3,
        "favorites": 3,
        "mid": 4587498,
        "author": "Mickytown",
        "description": "12.24P&amp;amp;T普泰广场活力开业！",
        "create": "2016-10-30 11:46",
        "pic": "http://i1.hdslb.com/bfs/archive/68874d667d9e7b0e8cad27bef9320ebc2ac51dcf.jpg_320x200.jpg",
        "coins": 1,
        "duration": "4:34",
        "badgepay": false,
        "pts": 222
      },
      {
        "aid": "6864684",
        "typename": "广告",
        "title": "撩妹吃豆腐专车 丰田86漂移对决AE86·洗脑神车广告",
        "subtitle": "",
        "play": 174,
        "review": 0,
        "video_review": 2,
        "favorites": 4,
        "mid": 26401622,
        "author": "关你车事",
        "description": "从老款的86漂移躲避激光武器广告开始，到最新的86一镜到底不露车外观和真实动漫随时切换的广告，都在不停换着玩法告诉大家这车到底有多好玩。别说廉价车没什么乐趣，新86的4款车型官方指导价才24.98万--28.78万元，绝对算得上是平民级跑车，但全世界没有一个车手会认为这台“廉价车”没有乐趣！",
        "create": "2016-10-29 01:18",
        "pic": "http://i0.hdslb.com/bfs/archive/9080fb84a7ea665b9c660826f06257995767d996.png_320x200.png",
        "coins": 0,
        "duration": "4:47",
        "badgepay": false,
        "pts": 196
      },
      {
        "aid": "6844634",
        "typename": "广告",
        "title": "【SNH48】途虎养车五周年逐帧动画广告",
        "subtitle": "",
        "play": 143,
        "review": 0,
        "video_review": 2,
        "favorites": 4,
        "mid": 52229078,
        "author": "月月爱车",
        "description": "【SNH48】途虎养车五周年逐帧动画广告",
        "create": "2016-10-27 15:47",
        "pic": "http://i0.hdslb.com/bfs/archive/2df84634fadaf6b1dbe1e0935e174070c978748e.png_320x200.png",
        "coins": 34,
        "duration": "0:24",
        "badgepay": false,
        "pts": 166
      },
      {
        "aid": "6844649",
        "typename": "广告",
        "title": "【汽车】广汽传祺GS8和宝马，这是要打架？",
        "subtitle": "",
        "play": 143,
        "review": 0,
        "video_review": 0,
        "favorites": 2,
        "mid": 39252302,
        "author": "因赛集团小橙C",
        "description": "广汽传祺GS8上市宣传片，唯一能征服自己的路，叫尽逐前路b(￣▽￣)d",
        "create": "2016-10-27 15:48",
        "pic": "http://i0.hdslb.com/bfs/archive/edf7f191a48481307a6bbf1f189b179c9ab1d671.jpg_320x200.jpg",
        "coins": 0,
        "duration": "1:38",
        "badgepay": false,
        "pts": 132
      },
      {
        "aid": "6880806",
        "typename": "广告",
        "title": "你多久没被满足了？",
        "subtitle": "",
        "play": 99,
        "review": 0,
        "video_review": 0,
        "favorites": 0,
        "mid": 35109778,
        "author": "哗啦哗啦我是飞饼",
        "description": "永和豆浆搞笑视频",
        "create": "2016-10-30 00:22",
        "pic": "http://i2.hdslb.com/bfs/archive/aab37d0d3df05774198dd6907b73fb00c9b6220c.png_320x200.png",
        "coins": 0,
        "duration": "1:06",
        "badgepay": false,
        "pts": 86
      }
    ]
  }
}